app/__init__.py
app/manage.py
app/models.py
app/settings.py
app/urls.py
ripda/__init__.py
ripda/__main__.py
ripda/conf/__init__.py
ripda/conf/global_settings.py
ripda/core/__init__.py
ripda/core/management/__init__.py
ripda/core/management/commands/__init__.py
ripda/core/management/commands/migrate.py
ripda/core/management/commands/miner.py
ripda/core/management/commands/populate.py
ripda/core/management/commands/runserver.py
ripda/db/__init__.py
ripda/db/engine.py
ripda/db/session.py
ripda/db/models/__init__.py
ripda/db/models/block.py
ripda/db/models/block_transaction.py
ripda/db/models/transaction.py
ripda/utils/__init__.py
ripda/utils/functools.py
ripda/utils/version.py
ripda-1.0.0a2.dist-info/LICENSE.txt
ripda-1.0.0a2.dist-info/METADATA
ripda-1.0.0a2.dist-info/WHEEL
ripda-1.0.0a2.dist-info/entry_points.txt
ripda-1.0.0a2.dist-info/top_level.txt
ripda-1.0.0a2.dist-info/RECORD
