Metadata-Version: 2.1
Name: ripda
Version: 1.0.0a2
Summary: Ripda Core integration
Home-page: https://github.com/isakruas/ripda
Author: Isak Paulo de Andrade Ruas
Author-email: isakruas@gmail.com
License: MIT
Project-URL: Documentation, https://ripda.readthedocs.io/en/latest/
Project-URL: Source, https://github.com/isakruas/ripda/
Project-URL: Bug Reports, https://github.com/isakruas/ripda/issues
Platform: UNKNOWN
Classifier: Development Status :: 1 - Planning
Classifier: Intended Audience :: Developers
Classifier: Topic :: Software Development :: Build Tools
Classifier: License :: OSI Approved :: MIT License
Classifier: Operating System :: OS Independent
Classifier: Programming Language :: Python
Classifier: Programming Language :: Python :: 3.10
Classifier: Topic :: Internet :: WWW/HTTP
Classifier: Topic :: Internet :: WWW/HTTP :: Dynamic Content
Classifier: Topic :: Software Development :: Libraries :: Application Frameworks
Classifier: Topic :: Software Development :: Libraries :: Python Modules
Requires-Python: >=3.10
License-File: LICENSE.txt
Requires-Dist: ecutils
Requires-Dist: fastapi
Requires-Dist: uvicorn[standard]
Requires-Dist: sqlmodel
Requires-Dist: tqdm
Requires-Dist: asyncpg
